tkmetro/MetroFramework.Design.dll
tkmetro/MetroFramework.Fonts.dll
tkmetro/MetroFramework.dll
tkmetro/__init__.py
tkmetro/base.py
tkmetro/mult.py
tkmetro-1.1.0.dist-info/METADATA
tkmetro-1.1.0.dist-info/WHEEL
tkmetro-1.1.0.dist-info/top_level.txt
tkmetro-1.1.0.dist-info/RECORD
