Metadata-Version: 2.1
Name: tkmetro
Version: 1.1.0
Summary: tkinter with metroframework
Author: XiangQinxi
Author-email: XiangQinxi@outlook.com
Classifier: Programming Language :: Python :: 3
Classifier: License :: OSI Approved :: MIT License
Classifier: Operating System :: OS Independent
Requires: pythonnet
Requires-Python: >=3
